pashto_stopwords/__init__.py
pashto_stopwords/__main__.py
pashto_stopwords/pashto-stopwords.txt
pashto_stopwords-1.0.0.dist-info/licenses/LICENSE
pashto_stopwords-1.0.0.dist-info/METADATA
pashto_stopwords-1.0.0.dist-info/WHEEL
pashto_stopwords-1.0.0.dist-info/entry_points.txt
pashto_stopwords-1.0.0.dist-info/top_level.txt
pashto_stopwords-1.0.0.dist-info/RECORD
