Metadata-Version: 2.4
Name: pashto-stopwords
Version: 1.0.0
Summary: د پښتو ژبې لومړنی معیاري بند-کلمو کارپس
Author-email: "IPashto.AI" <ipashto.ai@gmail.com>
License: MIT
Project-URL: Homepage, https://github.com/spinzar/pashto-stopwords
Keywords: pashto,nlp,stopwords,ai,پښتو
Classifier: Programming Language :: Python :: 3
Classifier: Operating System :: OS Independent
Classifier: Topic :: Text Processing :: Linguistic
Requires-Python: >=3.7
License-File: LICENSE
Dynamic: license-file
